twrapform/__init__.py
twrapform/_common.py
twrapform/_lock.py
twrapform/_logging.py
twrapform/exception.py
twrapform/result.py
twrapform/workflow.py
twrapform/options/__init__.py
twrapform/options/opt_name.py
twrapform/options/opt_value.py
twrapform/options/options.py
twrapform/options/types.py
twrapform-0.1.2.dist-info/METADATA
twrapform-0.1.2.dist-info/WHEEL
twrapform-0.1.2.dist-info/licenses/LICENSE
twrapform-0.1.2.dist-info/RECORD
