Metadata-Version: 2.4
Name: twrapform
Version: 0.1.2
Summary: Terraform task management wrapper for Python
Project-URL: Repository, https://github.com/minthem/twrapform
License-File: LICENSE
Requires-Python: >=3.10
Requires-Dist: python-hcl2
